{"saved_at": 1774537786.651536, "ttl": 14400, "type": "dataframe", "data": [{"date": "2025-10-27", "stock_id": "3017", "Trading_Volume": 5918927, "Trading_money": 7066053735, "open": 1205.0, "max": 1220.0, "min": 1180.0, "close": 1190.0, "spread": 20.0, "Trading_turnover": 8463}, {"date": "2025-10-28", "stock_id": "3017", "Trading_Volume": 13577543, "Trading_money": 17473193745, "open": 1245.0, "max": 1305.0, "min": 1240.0, "close": 1300.0, "spread": 110.0, "Trading_turnover": 25273}, {"date": "2025-10-29", "stock_id": "3017", "Trading_Volume": 7916687, "Trading_money": 10420710390, "open": 1320.0, "max": 1335.0, "min": 1290.0, "close": 1330.0, "spread": 30.0, "Trading_turnover": 13609}, {"date": "2025-10-30", "stock_id": "3017", "Trading_Volume": 11618364, "Trading_money": 16233953960, "open": 1370.0, "max": 1425.0, "min": 1360.0, "close": 1410.0, "spread": 80.0, "Trading_turnover": 18756}, {"date": "2025-10-31", "stock_id": "3017", "Trading_Volume": 6889584, "Trading_money": 9797582055, "open": 1440.0, "max": 1440.0, "min": 1395.0, "close": 1425.0, "spread": 15.0, "Trading_turnover": 12448}, {"date": "2025-11-03", "stock_id": "3017", "Trading_Volume": 6609856, "Trading_money": 9742543915, "open": 1450.0, "max": 1495.0, "min": 1445.0, "close": 1495.0, "spread": 70.0, "Trading_turnover": 11693}, {"date": "2025-11-04", "stock_id": "3017", "Trading_Volume": 5815364, "Trading_money": 8510197505, "open": 1510.0, "max": 1510.0, "min": 1430.0, "close": 1435.0, "spread": -60.0, "Trading_turnover": 16512}, {"date": "2025-11-05", "stock_id": "3017", "Trading_Volume": 11014399, "Trading_money": 15913893775, "open": 1395.0, "max": 1475.0, "min": 1390.0, "close": 1445.0, "spread": 10.0, "Trading_turnover": 17201}, {"date": "2025-11-06", "stock_id": "3017", "Trading_Volume": 6544619, "Trading_money": 9775429695, "open": 1485.0, "max": 1510.0, "min": 1470.0, "close": 1495.0, "spread": 50.0, "Trading_turnover": 11894}, {"date": "2025-11-07", "stock_id": "3017", "Trading_Volume": 6163276, "Trading_money": 9151295990, "open": 1480.0, "max": 1510.0, "min": 1465.0, "close": 1465.0, "spread": -30.0, "Trading_turnover": 11171}, {"date": "2025-11-10", "stock_id": "3017", "Trading_Volume": 8217203, "Trading_money": 12520194725, "open": 1505.0, "max": 1570.0, "min": 1460.0, "close": 1550.0, "spread": 85.0, "Trading_turnover": 15126}, {"date": "2025-11-11", "stock_id": "3017", "Trading_Volume": 7563454, "Trading_money": 11707943295, "open": 1560.0, "max": 1570.0, "min": 1520.0, "close": 1540.0, "spread": -10.0, "Trading_turnover": 15198}, {"date": "2025-11-12", "stock_id": "3017", "Trading_Volume": 7957940, "Trading_money": 12200641990, "open": 1555.0, "max": 1585.0, "min": 1500.0, "close": 1505.0, "spread": -35.0, "Trading_turnover": 16985}, {"date": "2025-11-13", "stock_id": "3017", "Trading_Volume": 6776412, "Trading_money": 10088952570, "open": 1505.0, "max": 1515.0, "min": 1470.0, "close": 1495.0, "spread": -10.0, "Trading_turnover": 16429}, {"date": "2025-11-14", "stock_id": "3017", "Trading_Volume": 9611190, "Trading_money": 13660645660, "open": 1435.0, "max": 1455.0, "min": 1400.0, "close": 1420.0, "spread": -75.0, "Trading_turnover": 26590}, {"date": "2025-11-17", "stock_id": "3017", "Trading_Volume": 5124431, "Trading_money": 7324452315, "open": 1435.0, "max": 1460.0, "min": 1410.0, "close": 1420.0, "spread": 0.0, "Trading_turnover": 10260}, {"date": "2025-11-18", "stock_id": "3017", "Trading_Volume": 5798659, "Trading_money": 8045522250, "open": 1400.0, "max": 1410.0, "min": 1370.0, "close": 1370.0, "spread": -50.0, "Trading_turnover": 15932}, {"date": "2025-11-19", "stock_id": "3017", "Trading_Volume": 5470504, "Trading_money": 7419596945, "open": 1355.0, "max": 1385.0, "min": 1335.0, "close": 1340.0, "spread": -30.0, "Trading_turnover": 13457}, {"date": "2025-11-20", "stock_id": "3017", "Trading_Volume": 9005212, "Trading_money": 12297418710, "open": 1420.0, "max": 1420.0, "min": 1330.0, "close": 1335.0, "spread": -5.0, "Trading_turnover": 19534}, {"date": "2025-11-21", "stock_id": "3017", "Trading_Volume": 13052742, "Trading_money": 16068223615, "open": 1250.0, "max": 1280.0, "min": 1205.0, "close": 1240.0, "spread": -95.0, "Trading_turnover": 34145}, {"date": "2025-11-24", "stock_id": "3017", "Trading_Volume": 8138459, "Trading_money": 10016493895, "open": 1260.0, "max": 1260.0, "min": 1210.0, "close": 1245.0, "spread": 5.0, "Trading_turnover": 15487}, {"date": "2025-11-25", "stock_id": "3017", "Trading_Volume": 10653298, "Trading_money": 13747004185, "open": 1300.0, "max": 1340.0, "min": 1240.0, "close": 1315.0, "spread": 70.0, "Trading_turnover": 18525}, {"date": "2025-11-26", "stock_id": "3017", "Trading_Volume": 8361725, "Trading_money": 11452737005, "open": 1350.0, "max": 1390.0, "min": 1340.0, "close": 1385.0, "spread": 70.0, "Trading_turnover": 16957}, {"date": "2025-11-27", "stock_id": "3017", "Trading_Volume": 6696881, "Trading_money": 9337940160, "open": 1400.0, "max": 1420.0, "min": 1370.0, "close": 1395.0, "spread": 10.0, "Trading_turnover": 13926}, {"date": "2025-11-28", "stock_id": "3017", "Trading_Volume": 4674610, "Trading_money": 6498432335, "open": 1405.0, "max": 1410.0, "min": 1375.0, "close": 1375.0, "spread": -20.0, "Trading_turnover": 12414}, {"date": "2025-12-01", "stock_id": "3017", "Trading_Volume": 4953191, "Trading_money": 6674854415, "open": 1380.0, "max": 1385.0, "min": 1330.0, "close": 1340.0, "spread": -35.0, "Trading_turnover": 14481}, {"date": "2025-12-02", "stock_id": "3017", "Trading_Volume": 7665974, "Trading_money": 10381696540, "open": 1360.0, "max": 1410.0, "min": 1310.0, "close": 1315.0, "spread": -25.0, "Trading_turnover": 19341}, {"date": "2025-12-03", "stock_id": "3017", "Trading_Volume": 5764345, "Trading_money": 7788445300, "open": 1340.0, "max": 1365.0, "min": 1320.0, "close": 1355.0, "spread": 40.0, "Trading_turnover": 8704}, {"date": "2025-12-04", "stock_id": "3017", "Trading_Volume": 5497875, "Trading_money": 7425224125, "open": 1370.0, "max": 1385.0, "min": 1325.0, "close": 1325.0, "spread": -30.0, "Trading_turnover": 11777}, {"date": "2025-12-05", "stock_id": "3017", "Trading_Volume": 8314708, "Trading_money": 11465832580, "open": 1345.0, "max": 1405.0, "min": 1340.0, "close": 1385.0, "spread": 60.0, "Trading_turnover": 14479}, {"date": "2025-12-08", "stock_id": "3017", "Trading_Volume": 3875456, "Trading_money": 5381102435, "open": 1400.0, "max": 1400.0, "min": 1370.0, "close": 1385.0, "spread": 0.0, "Trading_turnover": 7474}, {"date": "2025-12-09", "stock_id": "3017", "Trading_Volume": 6722511, "Trading_money": 9465023720, "open": 1400.0, "max": 1430.0, "min": 1380.0, "close": 1410.0, "spread": 25.0, "Trading_turnover": 12052}, {"date": "2025-12-10", "stock_id": "3017", "Trading_Volume": 4737458, "Trading_money": 6710823195, "open": 1415.0, "max": 1430.0, "min": 1390.0, "close": 1425.0, "spread": 15.0, "Trading_turnover": 9404}, {"date": "2025-12-11", "stock_id": "3017", "Trading_Volume": 6854831, "Trading_money": 9802328950, "open": 1445.0, "max": 1450.0, "min": 1405.0, "close": 1430.0, "spread": 5.0, "Trading_turnover": 13192}, {"date": "2025-12-12", "stock_id": "3017", "Trading_Volume": 5865475, "Trading_money": 8510179035, "open": 1460.0, "max": 1485.0, "min": 1425.0, "close": 1425.0, "spread": -5.0, "Trading_turnover": 10942}, {"date": "2025-12-15", "stock_id": "3017", "Trading_Volume": 5675750, "Trading_money": 7815851285, "open": 1375.0, "max": 1390.0, "min": 1365.0, "close": 1380.0, "spread": -45.0, "Trading_turnover": 16973}, {"date": "2025-12-16", "stock_id": "3017", "Trading_Volume": 4565277, "Trading_money": 6204501320, "open": 1365.0, "max": 1390.0, "min": 1340.0, "close": 1345.0, "spread": -35.0, "Trading_turnover": 13214}, {"date": "2025-12-17", "stock_id": "3017", "Trading_Volume": 2963422, "Trading_money": 4005968095, "open": 1350.0, "max": 1380.0, "min": 1340.0, "close": 1340.0, "spread": -5.0, "Trading_turnover": 7533}, {"date": "2025-12-18", "stock_id": "3017", "Trading_Volume": 1937359, "Trading_money": 2605663235, "open": 1330.0, "max": 1365.0, "min": 1325.0, "close": 1360.0, "spread": 20.0, "Trading_turnover": 5101}, {"date": "2025-12-19", "stock_id": "3017", "Trading_Volume": 6314924, "Trading_money": 8971550145, "open": 1385.0, "max": 1450.0, "min": 1380.0, "close": 1450.0, "spread": 90.0, "Trading_turnover": 15026}, {"date": "2025-12-22", "stock_id": "3017", "Trading_Volume": 5388668, "Trading_money": 8009926700, "open": 1495.0, "max": 1505.0, "min": 1465.0, "close": 1475.0, "spread": 25.0, "Trading_turnover": 13344}, {"date": "2025-12-23", "stock_id": "3017", "Trading_Volume": 4084157, "Trading_money": 6120438780, "open": 1485.0, "max": 1510.0, "min": 1475.0, "close": 1510.0, "spread": 35.0, "Trading_turnover": 10671}, {"date": "2025-12-24", "stock_id": "3017", "Trading_Volume": 2659963, "Trading_money": 3990098495, "open": 1520.0, "max": 1525.0, "min": 1485.0, "close": 1500.0, "spread": -10.0, "Trading_turnover": 8395}, {"date": "2025-12-26", "stock_id": "3017", "Trading_Volume": 2493370, "Trading_money": 3757314985, "open": 1505.0, "max": 1520.0, "min": 1495.0, "close": 1520.0, "spread": 20.0, "Trading_turnover": 7100}, {"date": "2025-12-29", "stock_id": "3017", "Trading_Volume": 3494079, "Trading_money": 5354561885, "open": 1520.0, "max": 1550.0, "min": 1505.0, "close": 1545.0, "spread": 25.0, "Trading_turnover": 9515}, {"date": "2025-12-30", "stock_id": "3017", "Trading_Volume": 1929146, "Trading_money": 2961234895, "open": 1530.0, "max": 1550.0, "min": 1525.0, "close": 1530.0, "spread": -15.0, "Trading_turnover": 5488}, {"date": "2025-12-31", "stock_id": "3017", "Trading_Volume": 3301831, "Trading_money": 5046034645, "open": 1530.0, "max": 1560.0, "min": 1510.0, "close": 1510.0, "spread": -20.0, "Trading_turnover": 8572}, {"date": "2026-01-02", "stock_id": "3017", "Trading_Volume": 5780257, "Trading_money": 8489042455, "open": 1535.0, "max": 1540.0, "min": 1440.0, "close": 1455.0, "spread": -55.0, "Trading_turnover": 20772}, {"date": "2026-01-05", "stock_id": "3017", "Trading_Volume": 4412179, "Trading_money": 6391480390, "open": 1450.0, "max": 1465.0, "min": 1430.0, "close": 1450.0, "spread": -5.0, "Trading_turnover": 14307}, {"date": "2026-01-06", "stock_id": "3017", "Trading_Volume": 6635971, "Trading_money": 9483708785, "open": 1480.0, "max": 1490.0, "min": 1410.0, "close": 1425.0, "spread": -25.0, "Trading_turnover": 19287}, {"date": "2026-01-07", "stock_id": "3017", "Trading_Volume": 8590829, "Trading_money": 11985918760, "open": 1440.0, "max": 1460.0, "min": 1375.0, "close": 1375.0, "spread": -50.0, "Trading_turnover": 34339}, {"date": "2026-01-08", "stock_id": "3017", "Trading_Volume": 7760960, "Trading_money": 10689978190, "open": 1350.0, "max": 1410.0, "min": 1345.0, "close": 1355.0, "spread": -20.0, "Trading_turnover": 22197}, {"date": "2026-01-09", "stock_id": "3017", "Trading_Volume": 6867721, "Trading_money": 9535800465, "open": 1370.0, "max": 1415.0, "min": 1360.0, "close": 1375.0, "spread": 20.0, "Trading_turnover": 16110}, {"date": "2026-01-12", "stock_id": "3017", "Trading_Volume": 5695057, "Trading_money": 7775639930, "open": 1395.0, "max": 1400.0, "min": 1340.0, "close": 1355.0, "spread": -20.0, "Trading_turnover": 21503}, {"date": "2026-01-13", "stock_id": "3017", "Trading_Volume": 4710863, "Trading_money": 6394771428, "open": 1375.0, "max": 1390.0, "min": 1335.0, "close": 1345.0, "spread": -10.0, "Trading_turnover": 17104}, {"date": "2026-01-14", "stock_id": "3017", "Trading_Volume": 6359542, "Trading_money": 8942176975, "open": 1365.0, "max": 1425.0, "min": 1360.0, "close": 1420.0, "spread": 75.0, "Trading_turnover": 16191}, {"date": "2026-01-15", "stock_id": "3017", "Trading_Volume": 5284664, "Trading_money": 7300102445, "open": 1420.0, "max": 1425.0, "min": 1360.0, "close": 1380.0, "spread": -40.0, "Trading_turnover": 16231}, {"date": "2026-01-16", "stock_id": "3017", "Trading_Volume": 4857493, "Trading_money": 6626400820, "open": 1395.0, "max": 1395.0, "min": 1350.0, "close": 1360.0, "spread": -20.0, "Trading_turnover": 15959}, {"date": "2026-01-19", "stock_id": "3017", "Trading_Volume": 9552812, "Trading_money": 12409257815, "open": 1355.0, "max": 1360.0, "min": 1275.0, "close": 1280.0, "spread": -80.0, "Trading_turnover": 47325}, {"date": "2026-01-20", "stock_id": "3017", "Trading_Volume": 4832354, "Trading_money": 6217964285, "open": 1275.0, "max": 1305.0, "min": 1265.0, "close": 1295.0, "spread": 15.0, "Trading_turnover": 13136}, {"date": "2026-01-21", "stock_id": "3017", "Trading_Volume": 3616028, "Trading_money": 4671666900, "open": 1285.0, "max": 1310.0, "min": 1280.0, "close": 1280.0, "spread": -15.0, "Trading_turnover": 11609}, {"date": "2026-01-22", "stock_id": "3017", "Trading_Volume": 7901222, "Trading_money": 10567497865, "open": 1320.0, "max": 1370.0, "min": 1265.0, "close": 1355.0, "spread": 75.0, "Trading_turnover": 19468}, {"date": "2026-01-23", "stock_id": "3017", "Trading_Volume": 4242687, "Trading_money": 5805203913, "open": 1385.0, "max": 1385.0, "min": 1355.0, "close": 1375.0, "spread": 20.0, "Trading_turnover": 10006}, {"date": "2026-01-26", "stock_id": "3017", "Trading_Volume": 4133584, "Trading_money": 5719309050, "open": 1390.0, "max": 1405.0, "min": 1365.0, "close": 1370.0, "spread": -5.0, "Trading_turnover": 9725}, {"date": "2026-01-27", "stock_id": "3017", "Trading_Volume": 6606873, "Trading_money": 9370966435, "open": 1380.0, "max": 1440.0, "min": 1375.0, "close": 1420.0, "spread": 50.0, "Trading_turnover": 17358}, {"date": "2026-01-28", "stock_id": "3017", "Trading_Volume": 5845271, "Trading_money": 8485076555, "open": 1445.0, "max": 1470.0, "min": 1430.0, "close": 1465.0, "spread": 45.0, "Trading_turnover": 14912}, {"date": "2026-01-29", "stock_id": "3017", "Trading_Volume": 9257577, "Trading_money": 13759185210, "open": 1480.0, "max": 1510.0, "min": 1450.0, "close": 1495.0, "spread": 30.0, "Trading_turnover": 23344}, {"date": "2026-01-30", "stock_id": "3017", "Trading_Volume": 6913370, "Trading_money": 9946713945, "open": 1490.0, "max": 1495.0, "min": 1400.0, "close": 1460.0, "spread": -35.0, "Trading_turnover": 18337}, {"date": "2026-02-02", "stock_id": "3017", "Trading_Volume": 7071740, "Trading_money": 10437827835, "open": 1440.0, "max": 1505.0, "min": 1415.0, "close": 1490.0, "spread": 30.0, "Trading_turnover": 17818}, {"date": "2026-02-03", "stock_id": "3017", "Trading_Volume": 14952322, "Trading_money": 23901100955, "open": 1550.0, "max": 1635.0, "min": 1545.0, "close": 1635.0, "spread": 145.0, "Trading_turnover": 37042}, {"date": "2026-02-04", "stock_id": "3017", "Trading_Volume": 10085080, "Trading_money": 16811953680, "open": 1645.0, "max": 1710.0, "min": 1625.0, "close": 1675.0, "spread": 40.0, "Trading_turnover": 21700}, {"date": "2026-02-05", "stock_id": "3017", "Trading_Volume": 6535909, "Trading_money": 10892515541, "open": 1665.0, "max": 1720.0, "min": 1630.0, "close": 1630.0, "spread": -45.0, "Trading_turnover": 16842}, {"date": "2026-02-06", "stock_id": "3017", "Trading_Volume": 6375872, "Trading_money": 10111056350, "open": 1605.0, "max": 1625.0, "min": 1535.0, "close": 1595.0, "spread": -35.0, "Trading_turnover": 18525}, {"date": "2026-02-09", "stock_id": "3017", "Trading_Volume": 5674608, "Trading_money": 9202968900, "open": 1680.0, "max": 1680.0, "min": 1585.0, "close": 1600.0, "spread": 5.0, "Trading_turnover": 17444}, {"date": "2026-02-10", "stock_id": "3017", "Trading_Volume": 3737625, "Trading_money": 6021530620, "open": 1625.0, "max": 1645.0, "min": 1590.0, "close": 1620.0, "spread": 20.0, "Trading_turnover": 8902}, {"date": "2026-02-11", "stock_id": "3017", "Trading_Volume": 3294642, "Trading_money": 5266533000, "open": 1610.0, "max": 1620.0, "min": 1560.0, "close": 1605.0, "spread": -15.0, "Trading_turnover": 10183}, {"date": "2026-02-23", "stock_id": "3017", "Trading_Volume": 6287420, "Trading_money": 9769752650, "open": 1650.0, "max": 1650.0, "min": 1515.0, "close": 1520.0, "spread": -85.0, "Trading_turnover": 29065}, {"date": "2026-02-24", "stock_id": "3017", "Trading_Volume": 4176128, "Trading_money": 6414465095, "open": 1535.0, "max": 1560.0, "min": 1510.0, "close": 1550.0, "spread": 30.0, "Trading_turnover": 12284}, {"date": "2026-02-25", "stock_id": "3017", "Trading_Volume": 8984346, "Trading_money": 14809374795, "open": 1565.0, "max": 1695.0, "min": 1560.0, "close": 1675.0, "spread": 125.0, "Trading_turnover": 24958}, {"date": "2026-02-26", "stock_id": "3017", "Trading_Volume": 10544482, "Trading_money": 18338271690, "open": 1680.0, "max": 1785.0, "min": 1665.0, "close": 1765.0, "spread": 90.0, "Trading_turnover": 23134}, {"date": "2026-03-02", "stock_id": "3017", "Trading_Volume": 5311930, "Trading_money": 9409524235, "open": 1720.0, "max": 1800.0, "min": 1715.0, "close": 1765.0, "spread": 0.0, "Trading_turnover": 12972}, {"date": "2026-03-03", "stock_id": "3017", "Trading_Volume": 8804200, "Trading_money": 16185755980, "open": 1830.0, "max": 1910.0, "min": 1780.0, "close": 1795.0, "spread": 30.0, "Trading_turnover": 23617}, {"date": "2026-03-04", "stock_id": "3017", "Trading_Volume": 6886787, "Trading_money": 12036586325, "open": 1775.0, "max": 1795.0, "min": 1670.0, "close": 1750.0, "spread": -45.0, "Trading_turnover": 18351}, {"date": "2026-03-05", "stock_id": "3017", "Trading_Volume": 5484692, "Trading_money": 10145440390, "open": 1860.0, "max": 1900.0, "min": 1795.0, "close": 1820.0, "spread": 70.0, "Trading_turnover": 13163}, {"date": "2026-03-06", "stock_id": "3017", "Trading_Volume": 4254526, "Trading_money": 7835190860, "open": 1810.0, "max": 1885.0, "min": 1785.0, "close": 1845.0, "spread": 25.0, "Trading_turnover": 9816}, {"date": "2026-03-09", "stock_id": "3017", "Trading_Volume": 4090895, "Trading_money": 6840998490, "open": 1665.0, "max": 1700.0, "min": 1665.0, "close": 1665.0, "spread": -180.0, "Trading_turnover": 22758}, {"date": "2026-03-10", "stock_id": "3017", "Trading_Volume": 6547366, "Trading_money": 11174860850, "open": 1735.0, "max": 1745.0, "min": 1665.0, "close": 1695.0, "spread": 30.0, "Trading_turnover": 13975}, {"date": "2026-03-11", "stock_id": "3017", "Trading_Volume": 5418586, "Trading_money": 9859306450, "open": 1740.0, "max": 1860.0, "min": 1740.0, "close": 1860.0, "spread": 165.0, "Trading_turnover": 15699}, {"date": "2026-03-12", "stock_id": "3017", "Trading_Volume": 6700536, "Trading_money": 12775300075, "open": 1900.0, "max": 1955.0, "min": 1870.0, "close": 1875.0, "spread": 15.0, "Trading_turnover": 15003}, {"date": "2026-03-13", "stock_id": "3017", "Trading_Volume": 5993158, "Trading_money": 11284071615, "open": 1855.0, "max": 1930.0, "min": 1815.0, "close": 1865.0, "spread": -10.0, "Trading_turnover": 13010}, {"date": "2026-03-16", "stock_id": "3017", "Trading_Volume": 4314909, "Trading_money": 8094126872, "open": 1890.0, "max": 1920.0, "min": 1830.0, "close": 1830.0, "spread": -35.0, "Trading_turnover": 12601}, {"date": "2026-03-17", "stock_id": "3017", "Trading_Volume": 5606630, "Trading_money": 10715856695, "open": 1870.0, "max": 1970.0, "min": 1860.0, "close": 1905.0, "spread": 75.0, "Trading_turnover": 12937}, {"date": "2026-03-18", "stock_id": "3017", "Trading_Volume": 5543887, "Trading_money": 10498849744, "open": 1935.0, "max": 1955.0, "min": 1850.0, "close": 1850.0, "spread": -55.0, "Trading_turnover": 19177}, {"date": "2026-03-19", "stock_id": "3017", "Trading_Volume": 10256997, "Trading_money": 20359184885, "open": 1835.0, "max": 2035.0, "min": 1835.0, "close": 2015.0, "spread": 165.0, "Trading_turnover": 28171}, {"date": "2026-03-20", "stock_id": "3017", "Trading_Volume": 6991270, "Trading_money": 14028231360, "open": 2010.0, "max": 2060.0, "min": 1945.0, "close": 2050.0, "spread": 35.0, "Trading_turnover": 15320}, {"date": "2026-03-23", "stock_id": "3017", "Trading_Volume": 5032899, "Trading_money": 10003165310, "open": 1985.0, "max": 2045.0, "min": 1955.0, "close": 1995.0, "spread": -55.0, "Trading_turnover": 17344}, {"date": "2026-03-24", "stock_id": "3017", "Trading_Volume": 6721340, "Trading_money": 13285093275, "open": 2020.0, "max": 2030.0, "min": 1915.0, "close": 1945.0, "spread": -50.0, "Trading_turnover": 16040}, {"date": "2026-03-25", "stock_id": "3017", "Trading_Volume": 5596612, "Trading_money": 11561071315, "open": 2020.0, "max": 2100.0, "min": 2015.0, "close": 2100.0, "spread": 155.0, "Trading_turnover": 15086}, {"date": "2026-03-26", "stock_id": "3017", "Trading_Volume": 8504254, "Trading_money": 19327999055, "open": 2200.0, "max": 2310.0, "min": 2175.0, "close": 2275.0, "spread": 175.0, "Trading_turnover": 20963}]}