{"saved_at": 1774500668.818779, "ttl": 14400, "type": "dataframe", "data": [{"date": "2026-02-23", "stock_id": "6415", "Trading_Volume": 6939155, "Trading_money": 1979483798, "open": 286.5, "max": 293.5, "min": 277.0, "close": 284.5, "spread": 4.5, "Trading_turnover": 12976}, {"date": "2026-02-24", "stock_id": "6415", "Trading_Volume": 3667615, "Trading_money": 1049731141, "open": 284.0, "max": 290.5, "min": 282.0, "close": 285.0, "spread": 0.5, "Trading_turnover": 4110}, {"date": "2026-02-25", "stock_id": "6415", "Trading_Volume": 4606751, "Trading_money": 1289876774, "open": 285.5, "max": 288.0, "min": 276.0, "close": 279.0, "spread": -6.0, "Trading_turnover": 5894}, {"date": "2026-02-26", "stock_id": "6415", "Trading_Volume": 5114264, "Trading_money": 1453319698, "open": 280.0, "max": 291.5, "min": 279.0, "close": 281.0, "spread": 2.0, "Trading_turnover": 5301}, {"date": "2026-03-02", "stock_id": "6415", "Trading_Volume": 3393719, "Trading_money": 928055095, "open": 272.0, "max": 276.5, "min": 268.5, "close": 273.0, "spread": -8.0, "Trading_turnover": 4809}, {"date": "2026-03-03", "stock_id": "6415", "Trading_Volume": 6819994, "Trading_money": 1772241958, "open": 273.0, "max": 273.5, "min": 253.0, "close": 253.5, "spread": -19.5, "Trading_turnover": 8476}, {"date": "2026-03-04", "stock_id": "6415", "Trading_Volume": 6345299, "Trading_money": 1527841657, "open": 243.5, "max": 250.0, "min": 236.5, "close": 238.0, "spread": -15.5, "Trading_turnover": 6679}, {"date": "2026-03-05", "stock_id": "6415", "Trading_Volume": 4934759, "Trading_money": 1239547523, "open": 248.0, "max": 258.5, "min": 244.0, "close": 253.5, "spread": 15.5, "Trading_turnover": 5161}, {"date": "2026-03-06", "stock_id": "6415", "Trading_Volume": 3393018, "Trading_money": 855425709, "open": 253.0, "max": 259.5, "min": 247.0, "close": 252.5, "spread": -1.0, "Trading_turnover": 3349}, {"date": "2026-03-09", "stock_id": "6415", "Trading_Volume": 4094484, "Trading_money": 943596486, "open": 227.5, "max": 234.5, "min": 227.5, "close": 233.0, "spread": -19.5, "Trading_turnover": 4320}, {"date": "2026-03-10", "stock_id": "6415", "Trading_Volume": 3856865, "Trading_money": 956792312, "open": 243.0, "max": 256.0, "min": 237.5, "close": 252.5, "spread": 19.5, "Trading_turnover": 4186}, {"date": "2026-03-11", "stock_id": "6415", "Trading_Volume": 6166696, "Trading_money": 1611179105, "open": 253.0, "max": 269.0, "min": 252.0, "close": 262.0, "spread": 9.5, "Trading_turnover": 6997}, {"date": "2026-03-12", "stock_id": "6415", "Trading_Volume": 6877693, "Trading_money": 1846566933, "open": 260.5, "max": 278.0, "min": 258.0, "close": 272.0, "spread": 10.0, "Trading_turnover": 8588}, {"date": "2026-03-13", "stock_id": "6415", "Trading_Volume": 15668241, "Trading_money": 4380793402, "open": 270.0, "max": 286.5, "min": 269.0, "close": 280.0, "spread": 8.0, "Trading_turnover": 11916}, {"date": "2026-03-16", "stock_id": "6415", "Trading_Volume": 9791388, "Trading_money": 2609601593, "open": 287.0, "max": 289.0, "min": 258.0, "close": 262.5, "spread": -17.5, "Trading_turnover": 9650}, {"date": "2026-03-17", "stock_id": "6415", "Trading_Volume": 6306883, "Trading_money": 1711418588, "open": 268.0, "max": 276.0, "min": 265.0, "close": 274.5, "spread": 12.0, "Trading_turnover": 5923}, {"date": "2026-03-18", "stock_id": "6415", "Trading_Volume": 9139076, "Trading_money": 2630946872, "open": 281.0, "max": 294.0, "min": 276.5, "close": 289.5, "spread": 15.0, "Trading_turnover": 9507}, {"date": "2026-03-19", "stock_id": "6415", "Trading_Volume": 6754010, "Trading_money": 1941160605, "open": 285.0, "max": 297.0, "min": 280.0, "close": 280.5, "spread": -9.0, "Trading_turnover": 8685}, {"date": "2026-03-20", "stock_id": "6415", "Trading_Volume": 9928703, "Trading_money": 2893814197, "open": 285.0, "max": 300.5, "min": 282.5, "close": 286.0, "spread": 5.5, "Trading_turnover": 9508}, {"date": "2026-03-23", "stock_id": "6415", "Trading_Volume": 4311855, "Trading_money": 1212058707, "open": 277.0, "max": 288.5, "min": 277.0, "close": 278.5, "spread": -7.5, "Trading_turnover": 5239}, {"date": "2026-03-24", "stock_id": "6415", "Trading_Volume": 8664568, "Trading_money": 2532750169, "open": 300.0, "max": 303.0, "min": 280.5, "close": 282.5, "spread": 4.0, "Trading_turnover": 8413}, {"date": "2026-03-25", "stock_id": "6415", "Trading_Volume": 5565072, "Trading_money": 1642568816, "open": 293.0, "max": 299.5, "min": 288.0, "close": 293.5, "spread": 11.0, "Trading_turnover": 6808}]}