{"saved_at": 1774493915.98579, "ttl": 86400, "type": "dataframe", "data": [{"date": "2024-11-01", "stock_id": "1303", "country": "Taiwan", "revenue": 22758378000, "revenue_month": 10, "revenue_year": 2024}, {"date": "2024-12-01", "stock_id": "1303", "country": "Taiwan", "revenue": 21965473000, "revenue_month": 11, "revenue_year": 2024}, {"date": "2025-01-01", "stock_id": "1303", "country": "Taiwan", "revenue": 23431902000, "revenue_month": 12, "revenue_year": 2024}, {"date": "2025-02-01", "stock_id": "1303", "country": "Taiwan", "revenue": 20458289000, "revenue_month": 1, "revenue_year": 2025}, {"date": "2025-03-01", "stock_id": "1303", "country": "Taiwan", "revenue": 22080604000, "revenue_month": 2, "revenue_year": 2025}, {"date": "2025-04-01", "stock_id": "1303", "country": "Taiwan", "revenue": 23012738000, "revenue_month": 3, "revenue_year": 2025}, {"date": "2025-05-01", "stock_id": "1303", "country": "Taiwan", "revenue": 23176793000, "revenue_month": 4, "revenue_year": 2025}, {"date": "2025-06-01", "stock_id": "1303", "country": "Taiwan", "revenue": 21949304000, "revenue_month": 5, "revenue_year": 2025}, {"date": "2025-07-01", "stock_id": "1303", "country": "Taiwan", "revenue": 20589873000, "revenue_month": 6, "revenue_year": 2025}, {"date": "2025-08-01", "stock_id": "1303", "country": "Taiwan", "revenue": 21152898000, "revenue_month": 7, "revenue_year": 2025}, {"date": "2025-09-01", "stock_id": "1303", "country": "Taiwan", "revenue": 20853020000, "revenue_month": 8, "revenue_year": 2025}, {"date": "2025-10-01", "stock_id": "1303", "country": "Taiwan", "revenue": 22171572000, "revenue_month": 9, "revenue_year": 2025}, {"date": "2025-11-01", "stock_id": "1303", "country": "Taiwan", "revenue": 21229355000, "revenue_month": 10, "revenue_year": 2025}, {"date": "2025-12-01", "stock_id": "1303", "country": "Taiwan", "revenue": 21130715000, "revenue_month": 11, "revenue_year": 2025}, {"date": "2026-01-01", "stock_id": "1303", "country": "Taiwan", "revenue": 22097720000, "revenue_month": 12, "revenue_year": 2025}, {"date": "2026-02-01", "stock_id": "1303", "country": "Taiwan", "revenue": 22872625000, "revenue_month": 1, "revenue_year": 2026}, {"date": "2026-03-01", "stock_id": "1303", "country": "Taiwan", "revenue": 18556362000, "revenue_month": 2, "revenue_year": 2026}]}